horizon/__init__.py
horizon/backend/__init__.py
horizon/backend/__main__.py
horizon/backend/api/__init__.py
horizon/backend/api/handlers.py
horizon/backend/api/monitoring.py
horizon/backend/api/router.py
horizon/backend/api/v1/__init__.py
horizon/backend/api/v1/router/__init__.py
horizon/backend/api/v1/router/auth.py
horizon/backend/api/v1/router/hwm.py
horizon/backend/api/v1/router/hwm_history.py
horizon/backend/api/v1/router/namespace_history.py
horizon/backend/api/v1/router/namespaces.py
horizon/backend/api/v1/router/users.py
horizon/backend/db/__init__.py
horizon/backend/db/factory.py
horizon/backend/db/migrations/README
horizon/backend/db/migrations/__main__.py
horizon/backend/db/migrations/alembic.ini
horizon/backend/db/migrations/env.py
horizon/backend/db/migrations/script.py.mako
horizon/backend/db/migrations/versions/.keep
horizon/backend/db/migrations/versions/2023-10-09_b91de692624e_.py
horizon/backend/db/migrations/versions/2023-10-13_e29b66594970_.py
horizon/backend/db/migrations/versions/2023-10-16_edd2e353ca38_.py
horizon/backend/db/migrations/versions/2023-10-19_6b9001985cd2_.py
horizon/backend/db/migrations/versions/2023-11-24_dfce9f35c00e_.py
horizon/backend/db/migrations/versions/2023-12-23_4bc3fffc0209_.py
horizon/backend/db/migrations/versions/2024-02-22_c2d6da81f9ec_.py
horizon/backend/db/migrations/versions/2024-02-27_2452f82ae06c_.py
horizon/backend/db/migrations/versions/2024-02-27_5c7a5c5a193b_.py
horizon/backend/db/migrations/versions/2024-02-29_09be8fd79dbc_.py
horizon/backend/db/migrations/versions/2024-03-01_4c60578f3f1d_.py
horizon/backend/db/migrations/versions/2024-03-18_ec64f7b42221_.py
horizon/backend/db/mixins/__init__.py
horizon/backend/db/mixins/changed_by.py
horizon/backend/db/mixins/timestamp.py
horizon/backend/db/models/__init__.py
horizon/backend/db/models/base.py
horizon/backend/db/models/credentials_cache.py
horizon/backend/db/models/hwm.py
horizon/backend/db/models/hwm_history.py
horizon/backend/db/models/namespace.py
data_horizon-1.1.2.dist-info/LICENSE.txt
data_horizon-1.1.2.dist-info/METADATA
data_horizon-1.1.2.dist-info/WHEEL
data_horizon-1.1.2.dist-info/entry_points.txt
data_horizon-1.1.2.dist-info/RECORD
