Metadata-Version: 2.3
Name: data-horizon
Version: 1.1.2
Summary: Horizon REST API + client
License: Apache-2.0
Keywords: Horizon,REST,API,HWM
Author: DataOps.ETL
Author-email: onetools@mts.ru
Requires-Python: >=3.7,<4.0
Classifier: Development Status :: 5 - Production/Stable
Classifier: Framework :: FastAPI
Classifier: Framework :: Pydantic
Classifier: Framework :: Pydantic :: 1
Classifier: Framework :: Pydantic :: 2
Classifier: Intended Audience :: Developers
Classifier: License :: OSI Approved :: Apache Software License
Classifier: Operating System :: OS Independent
Classifier: Programming Language :: Python :: 3
Classifier: Programming Language :: Python :: 3.7
Classifier: Programming Language :: Python :: 3.8
Classifier: Programming Language :: Python :: 3.9
Classifier: Programming Language :: Python :: 3.10
Classifier: Programming Language :: Python :: 3.11
Classifier: Programming Language :: Python :: 3.12
Classifier: Programming Language :: Python :: 3.13
Classifier: Programming Language :: Python :: 3 :: Only
Classifier: Topic :: Software Development :: Libraries
Classifier: Topic :: Software Development :: Libraries :: Python Modules
Classifier: Typing :: Typed
Provides-Extra: backend
Provides-Extra: client-sync
Provides-Extra: ldap
Provides-Extra: postgres
Requires-Dist: alembic (<=1.12.1) ; (python_version == "3.7") and (extra == "backend")
Requires-Dist: alembic ; (python_version >= "3.8") and (extra == "backend")
Requires-Dist: anyio (<=3.7.1) ; (python_version == "3.7") and (extra == "backend")
Requires-Dist: anyio (<=4.5.2) ; (python_version == "3.8") and (extra == "backend")
Requires-Dist: anyio ; (python_version >= "3.9") and (extra == "backend")
Requires-Dist: argon2-cffi ; extra == "ldap"
Requires-Dist: asgi-correlation-id (<=4.2.0) ; (python_version == "3.7") and (extra == "backend")
Requires-Dist: asgi-correlation-id ; (python_version >= "3.8") and (extra == "backend")
Requires-Dist: asyncpg (<=0.28.0) ; (python_version == "3.7") and (extra == "postgres")
Requires-Dist: asyncpg ; (python_version >= "3.8") and (extra == "postgres")
Requires-Dist: authlib (<=1.2.1) ; (python_version == "3.7") and (extra == "backend" or extra == "client-sync")
Requires-Dist: authlib ; (python_version >= "3.8") and (extra == "backend" or extra == "client-sync")
Requires-Dist: bonsai (>=1.5.3) ; extra == "ldap"
Requires-Dist: cffi (>=1.15,<2.0) ; (python_version == "3.7") and (extra == "backend" or extra == "ldap" or extra == "client-sync")
Requires-Dist: cffi (>=1.17) ; (python_version >= "3.8") and (extra == "backend" or extra == "ldap" or extra == "client-sync")
Requires-Dist: coloredlogs ; extra == "backend"
Requires-Dist: devtools ; extra == "backend"
Requires-Dist: fastapi (>=0.103.0) ; (python_version >= "3.8") and (extra == "backend")
Requires-Dist: fastapi (>=0.103.2,<0.104.0) ; (python_version == "3.7") and (extra == "backend")
Requires-Dist: greenlet (>=3.1.1) ; extra == "backend"
Requires-Dist: importlib-resources (<=5.12.0) ; (python_version == "3.7") and (extra == "backend")
Requires-Dist: importlib-resources ; (python_version >= "3.8") and (extra == "backend")
Requires-Dist: mako (<=1.2.4) ; (python_version == "3.7") and (extra == "backend")
Requires-Dist: mako ; (python_version >= "3.8") and (extra == "backend")
Requires-Dist: markupsafe (<=2.1.5) ; (python_full_version <= "3.7.0") and (extra == "backend")
Requires-Dist: markupsafe ; (python_version >= "3.9") and (extra == "backend")
Requires-Dist: packaging (<=24.0) ; (python_version == "3.7") and (extra == "backend")
Requires-Dist: packaging ; (python_version >= "3.8") and (extra == "backend")
Requires-Dist: passlib ; extra == "backend"
Requires-Dist: pydantic (<2.6.0) ; python_version == "3.7"
Requires-Dist: pydantic (<3) ; python_version >= "3.8"
Requires-Dist: pydantic-settings (<=2.0.3) ; (python_version == "3.7") and (extra == "backend")
Requires-Dist: pydantic-settings ; (python_version >= "3.8") and (extra == "backend")
Requires-Dist: python-json-logger ; extra == "backend"
Requires-Dist: python-multipart (<=0.0.8) ; (python_version == "3.7") and (extra == "backend")
Requires-Dist: python-multipart ; (python_version >= "3.8") and (extra == "backend")
Requires-Dist: pyyaml ; extra == "backend"
Requires-Dist: requests (<=2.31.0) ; (python_version == "3.7") and (extra == "client-sync")
Requires-Dist: requests ; (python_version >= "3.8") and (extra == "client-sync")
Requires-Dist: sqlalchemy (>=2.0) ; extra == "backend"
Requires-Dist: sqlalchemy-utils ; extra == "backend"
Requires-Dist: starlette (<=0.29.0) ; (python_version == "3.7") and (extra == "backend")
Requires-Dist: starlette ; (python_version >= "3.8") and (extra == "backend")
Requires-Dist: starlette-exporter (<=0.17.1) ; (python_version == "3.7") and (extra == "backend")
Requires-Dist: starlette-exporter ; (python_version >= "3.8") and (extra == "backend")
Requires-Dist: typing-extensions (>=4.0.0) ; python_version >= "3.8"
Requires-Dist: typing-extensions (>=4.0.0,<4.8.0) ; python_version == "3.7"
Requires-Dist: urllib3 (>=1.26.0) ; extra == "client-sync"
Requires-Dist: uuid6 (<=2022.10.25) ; (python_version == "3.7") and (extra == "backend")
Requires-Dist: uuid6 ; (python_version >= "3.8") and (extra == "backend")
Requires-Dist: uvicorn (<=0.22.0) ; (python_version == "3.7") and (extra == "backend")
Requires-Dist: uvicorn ; (python_version >= "3.8") and (extra == "backend")
Project-URL: CI/CD, https://github.com/MobileTeleSystems/horizon/actions
Project-URL: Documentation, https://data-horizon.readthedocs.io/
Project-URL: Homepage, https://github.com/MobileTeleSystems/horizon
Project-URL: Source, https://github.com/MobileTeleSystems/horizon
Project-URL: Tracker, https://github.com/MobileTeleSystems/horizon/issues
